response.py
response-0.5.0.dist-info/LICENSE
response-0.5.0.dist-info/METADATA
response-0.5.0.dist-info/WHEEL
response-0.5.0.dist-info/top_level.txt
response-0.5.0.dist-info/RECORD
