Metadata-Version: 2.1
Name: response
Version: 0.5.0
Summary: Your handy frequency and impulse response processing object
Home-page: https://github.com/fhchl/Response
Author: Franz M. Heuchel
Author-email: franz.heuchel@gmail.com
License: MIT
Platform: UNKNOWN
Classifier: License :: OSI Approved :: MIT License
Classifier: Programming Language :: Python
Classifier: Programming Language :: Python :: 3
Classifier: Programming Language :: Python :: 3.6
Classifier: Programming Language :: Python :: 3.7
Classifier: Topic :: Multimedia :: Sound/Audio
Classifier: Topic :: Utilities
Requires-Python: >=3.6.0
Provides-Extra: dev
